README.rst
docs/.empty
examples/.empty
noxfile.py
pyproject.toml
scripts/.empty
decollator/__init__.py
decollator/__main__.py
decollator/cli.py
decollator-0.1.0.dist-info/entry_points.txt
decollator-0.1.0.dist-info/WHEEL
decollator-0.1.0.dist-info/METADATA
decollator-0.1.0.dist-info/RECORD
