Metadata-Version: 2.1
Name: decollator
Version: 0.1.0
Summary: changelog & stuff
Home-page: https://github.com/nicoretti/decollator
License: MIT
Keywords: changelog,cli,git
Author: Nicola Coretti
Author-email: nico.coretti@gmail.com
Requires-Python: >=3.7,<4.0
Classifier: Development Status :: 3 - Alpha
Classifier: Environment :: Console
Classifier: License :: OSI Approved :: MIT License
Classifier: Natural Language :: English
Classifier: Operating System :: OS Independent
Classifier: Programming Language :: Python :: 3
Classifier: Programming Language :: Python :: 3.7
Classifier: Programming Language :: Python :: 3.8
Classifier: Programming Language :: Python :: 3.9
Requires-Dist: tomli (>=2.0.1,<3.0.0)
Requires-Dist: tomli-w (>=1.0.0,<2.0.0)
Project-URL: Repository, https://github.com/nicoretti/decollator
